galaxy/__init__.py
galaxy/_version.py
galaxy/labextension/package.json
galaxy/labextension/static/372.d1faadab007f42e5557a.js
galaxy/labextension/static/431.ba88caa7d85b814a4809.js
galaxy/labextension/static/476.e1f5ed48331535b95e48.js
galaxy/labextension/static/541.f3abc0f21f89f59431a4.js
galaxy/labextension/static/728.e8e55babc6eb7a366b62.js
galaxy/labextension/static/remoteEntry.a8a9778ce586c6bf7f3c.js
galaxy/labextension/static/style.js
galaxy/labextension/static/third-party-licenses.json
galaxy_peach-2.0.10.data/data/share/jupyter/labextensions/galaxy/install.json
galaxy_peach-2.0.10.data/data/share/jupyter/labextensions/galaxy/package.json
galaxy_peach-2.0.10.data/data/share/jupyter/labextensions/galaxy/static/372.d1faadab007f42e5557a.js
galaxy_peach-2.0.10.data/data/share/jupyter/labextensions/galaxy/static/431.ba88caa7d85b814a4809.js
galaxy_peach-2.0.10.data/data/share/jupyter/labextensions/galaxy/static/476.e1f5ed48331535b95e48.js
galaxy_peach-2.0.10.data/data/share/jupyter/labextensions/galaxy/static/541.f3abc0f21f89f59431a4.js
galaxy_peach-2.0.10.data/data/share/jupyter/labextensions/galaxy/static/728.e8e55babc6eb7a366b62.js
galaxy_peach-2.0.10.data/data/share/jupyter/labextensions/galaxy/static/remoteEntry.a8a9778ce586c6bf7f3c.js
galaxy_peach-2.0.10.data/data/share/jupyter/labextensions/galaxy/static/style.js
galaxy_peach-2.0.10.data/data/share/jupyter/labextensions/galaxy/static/third-party-licenses.json
galaxy_peach-2.0.10.dist-info/METADATA
galaxy_peach-2.0.10.dist-info/WHEEL
galaxy_peach-2.0.10.dist-info/licenses/LICENSE
galaxy_peach-2.0.10.dist-info/RECORD
