Metadata-Version: 2.4
Name: galaxy-peach
Version: 2.0.10
Dynamic: Keywords
Summary: A JupyterLab extension.
Project-URL: Homepage, https://github.com/April-lemonade/Galaxy.git
Project-URL: Bug Tracker, https://github.com/April-lemonade/Galaxy.git/issues
Project-URL: Repository, https://github.com/April-lemonade/Galaxy.git.git
Author-email: Hongxin Fu <aprilf@mail.bnu.edu.cn>
License: BSD 3-Clause License
License-File: LICENSE
Classifier: Framework :: Jupyter
Classifier: Framework :: Jupyter :: JupyterLab
Classifier: Framework :: Jupyter :: JupyterLab :: 4
Classifier: Framework :: Jupyter :: JupyterLab :: Extensions
Classifier: Framework :: Jupyter :: JupyterLab :: Extensions :: Prebuilt
Classifier: License :: OSI Approved :: BSD License
Classifier: Programming Language :: Python
Classifier: Programming Language :: Python :: 3
Classifier: Programming Language :: Python :: 3.8
Classifier: Programming Language :: Python :: 3.9
Classifier: Programming Language :: Python :: 3.10
Classifier: Programming Language :: Python :: 3.11
Classifier: Programming Language :: Python :: 3.12
Requires-Python: >=3.8
